noaareport/__init__.py
noaareport/__main__.py
noaareport/noaareport.py
noaareport/test_report.py
noaareport/test_report_rbr.py
noaareport-0.2.1.dist-info/METADATA
noaareport-0.2.1.dist-info/RECORD
noaareport-0.2.1.dist-info/WHEEL
noaareport-0.2.1.dist-info/top_level.txt
