Metadata-Version: 2.1
Name: noaareport
Version: 0.2.1
Summary: A package to read noaa solar reports
Home-page: https://github.com/3ldr0n/noaa-report
Author: Edison Neto
Author-email: ednetoali@gmail.com
License: UNKNOWN
Platform: UNKNOWN
Classifier: Programming Language :: Python :: 3
Classifier: License :: OSI Approved :: MIT License
Classifier: Operating System :: OS Independent
Requires-Dist: pandas (>=0.21)
